bprof/__init__.py
bprof/_bprof.cpython-37m-darwin.so
bprof/cli.py
bprof/profile.py
bprof-0.5.2.dist-info/AUTHORS.rst
bprof-0.5.2.dist-info/LICENSE
bprof-0.5.2.dist-info/METADATA
bprof-0.5.2.dist-info/WHEEL
bprof-0.5.2.dist-info/entry_points.txt
bprof-0.5.2.dist-info/top_level.txt
bprof-0.5.2.dist-info/RECORD
