Metadata-Version: 2.1
Name: bprof
Version: 0.5.2
Summary: A Better PROFiler
Home-page: https://github.com/joelfrederico/bprof
Author: Joel Frederico
Author-email: joelfrederico@gmail.com
License: MIT license
Keywords: bprof
Platform: UNKNOWN
Classifier: Development Status :: 2 - Pre-Alpha
Classifier: Intended Audience :: Developers
Classifier: License :: OSI Approved :: MIT License
Classifier: Natural Language :: English
Classifier: Programming Language :: Python :: 3
Classifier: Programming Language :: Python :: 3.7
Requires-Python: >=3.7
